{
  "indexes": [
    {
      "collectionGroup": "leaveRequests",
      "queryScope": "COLLECTION",
      "fields": [
        {
          "fieldPath": "userId",
          "order": "ASCENDING"
        },
        {
          "fieldPath": "createdAt",
          "order": "DESCENDING"
        }
      ]
    },
    {
      "collectionGroup": "leaveRequests",
      "queryScope": "COLLECTION",
      "fields": [
        {
          "fieldPath": "status",
          "order": "ASCENDING"
        },
        {
          "fieldPath": "startDate",
          "order": "ASCENDING"
        }
      ]
    },
    {
      "collectionGroup": "leaveRequests",
      "queryScope": "COLLECTION", 
      "fields": [
        {
          "fieldPath": "status",
          "order": "ASCENDING"
        },
        {
          "fieldPath": "endDate",
          "order": "ASCENDING"
        }
      ]
    }
  ],
  "fieldOverrides": []
}